ssg/__about__.py
ssg/__init__.py
ssg/cli.py
ssg/ext.py
ssg/lib.py
ssg/ssg.py
ssg/__pycache__/__about__.cpython-311.pyc
ssg/__pycache__/__init__.cpython-311.pyc
ssg/__pycache__/cli.cpython-311.pyc
ssg/__pycache__/ext.cpython-311.pyc
ssg/__pycache__/kolibri.cpython-311.pyc
ssg/__pycache__/lib.cpython-311.pyc
ssg/__pycache__/migos.cpython-311.pyc
ssg/__pycache__/ssg.cpython-311.pyc
ssg/__pycache__/utils.cpython-311.pyc
ssg/skel/README.md
ssg/skel/ssg.yml
ssg/skel/data/articles.json
ssg/skel/data/cars.json
ssg/skel/data/generated.json
ssg/skel/data/readme.txt
ssg/skel/data/starwars_planets.json
ssg/skel/pages/_generated.html
ssg/skel/pages/about.html
ssg/skel/pages/advanced.html
ssg/skel/pages/article_generator.html
ssg/skel/pages/contact.html
ssg/skel/pages/error.html
ssg/skel/pages/index.html
ssg/skel/pages/info.md
ssg/skel/pages/redirectme.html
ssg/skel/pages/starwars_planet_generator.html
ssg/skel/pages/sub.html
ssg/skel/pages/folder2/index.html
ssg/skel/pages/folder2/join/new-stuff.html
ssg/skel/plugins/default.py
ssg/skel/public/robots.txt
ssg/skel/static/css/main.css
ssg/skel/static/images/kolibri.png
ssg/skel/static/js/main.js
ssg/skel/static/vendor/kolibri.css
ssg/skel/static/vendor/normalize.css
ssg/skel/templates/content/hello-world.md
ssg/skel/templates/content/more-details.md
ssg/skel/templates/content/readme.txt
ssg/skel/templates/layouts/default.html
ssg/skel/templates/partials/my_table.html
ssgpy-0.1.13.dist-info/LICENSE
ssgpy-0.1.13.dist-info/METADATA
ssgpy-0.1.13.dist-info/WHEEL
ssgpy-0.1.13.dist-info/entry_points.txt
ssgpy-0.1.13.dist-info/top_level.txt
ssgpy-0.1.13.dist-info/RECORD
