Metadata-Version: 2.1
Name: ssgpy
Version: 0.1.13
Summary: SSG is an elegant and modern static site generator for the common folks!
Home-page: https://github.com/mardix/ssg
Author: Mardix
Author-email: mardix@illybee.com
License: MIT
Keywords: static site generator
Platform: any
Classifier: Environment :: Web Environment
Classifier: Intended Audience :: Developers
Classifier: License :: OSI Approved :: BSD License
Classifier: Operating System :: OS Independent
Classifier: Programming Language :: Python
Classifier: Programming Language :: Python :: 2
Classifier: Programming Language :: Python :: 2.6
Classifier: Programming Language :: Python :: 2.7
Classifier: Programming Language :: Python :: 3
Classifier: Programming Language :: Python :: 3.3
Classifier: Programming Language :: Python :: 3.4
Classifier: Programming Language :: Python :: 3.5
Classifier: Topic :: Internet :: WWW/HTTP :: Dynamic Content
Classifier: Topic :: Software Development :: Libraries :: Python Modules
Requires-Python: >=3.8.0
License-File: LICENSE
Requires-Dist: click
Requires-Dist: arrow
Requires-Dist: jsmin
Requires-Dist: cssmin
Requires-Dist: pyyaml
Requires-Dist: pyScss
Requires-Dist: markdown
Requires-Dist: requests
Requires-Dist: livereload
Requires-Dist: jinja2 (>=3.0)
Requires-Dist: python-slugify
Requires-Dist: python-frontmatter
